

[{
    "text": "Pålidelig bærbar pc med et slankt, smart design.",
    "productname": "HP 14 bærbar - sølv ",
    "price": 2199,
    "fromprice": 3199,
    "tilbud": true,
    "img": "../images/hp.png"
  },
  {
    "text": "Spil de nyeste spilhits og PlayStation-ekslusive spil i fantastisk 4k.",
    "productname": "PS4 PRO Fornite inkl. Death Stranding",
    "price": 3199,
    "fromprice": null,
    "tilbud": false,
    "img": "../images/fortnite-ps4.png"
  },
  {
    "text": "B: 46 x H: 78 x D: 58 cm Minimumskøb 2 stk.",
    "productname": "Berlin spisebordsstol",
    "price": 229,
    "fromprice": 399,
    "tilbud": true,
    "img": "../images/stol.png"
  },
  {
    "text": "Maseratien med alt i udstyr fra gummihjul til lædersæde.",
    "productname": "Nordic Play Maserati Ghibli, 12V",
    "price": 1679,
    "fromprice": 2399,
    "tilbud": true,
    "img": "../images/maserati.png"
  }
]
